time_series.py
volatility_flat_price.py
volatility_spread.py
volatility_time_spread.py
volatility_underlying.py
pkg_calibration/__init__.py
pkg_calibration/time_series.py
pkg_calibration/volatility_flat_price.py
pkg_calibration/volatility_spread.py
pkg_calibration/volatility_time_spread.py
pkg_calibration/volatility_underlying.py
volatility/__init__.py
volatility/time_series.py
volatility/volatility_flat_price.py
volatility/volatility_spread.py
volatility/volatility_time_spread.py
volatility/volatility_underlying.py
pkg_calibration-0.1.3.dist-info/METADATA
pkg_calibration-0.1.3.dist-info/WHEEL
pkg_calibration-0.1.3.dist-info/top_level.txt
pkg_calibration-0.1.3.dist-info/RECORD
