Metadata-Version: 2.1
Name: pkg-calibration
Version: 0.1.3
Summary: Package To Calibrate Volatility Parameters
Author: Dieg Oatlib
License: UNKNOWN
Platform: UNKNOWN
Classifier: Programming Language :: Python :: 3
Classifier: License :: OSI Approved :: MIT License
Classifier: Operating System :: OS Independent
Requires-Python: >=3.8
Requires-Dist: numpy
Requires-Dist: pandas
Requires-Dist: numbers-parser
